pygmentslexerbabylon
