Metadata-Version: 1.1
Name: pygments-lexer-babylon
Version: 0.11.0
Summary: A javascript lexer for Pygments that uses the babylon parser
Home-page: https://github.com/rbann/pygments-lexer-babylon
Author: Richard Bann
Author-email: richard.bann@vertis.com
License: MIT
Keywords: pygments highlight jsx node babylon
Platform: UNKNOWN
Classifier: Environment :: Plugins
Classifier: Intended Audience :: Developers
Classifier: Programming Language :: Python :: 2
Classifier: Programming Language :: Python :: 3
